odoo/addons/purchase_sale_container_deposit_inter_company/README.rst
odoo/addons/purchase_sale_container_deposit_inter_company/__init__.py
odoo/addons/purchase_sale_container_deposit_inter_company/__manifest__.py
odoo/addons/purchase_sale_container_deposit_inter_company/i18n/fr.po
odoo/addons/purchase_sale_container_deposit_inter_company/i18n/it.po
odoo/addons/purchase_sale_container_deposit_inter_company/i18n/purchase_sale_container_deposit_inter_company.pot
odoo/addons/purchase_sale_container_deposit_inter_company/models/__init__.py
odoo/addons/purchase_sale_container_deposit_inter_company/models/purchase_order.py
odoo/addons/purchase_sale_container_deposit_inter_company/readme/CONTRIBUTORS.rst
odoo/addons/purchase_sale_container_deposit_inter_company/readme/DESCRIPTION.rst
odoo/addons/purchase_sale_container_deposit_inter_company/static/description/icon.png
odoo/addons/purchase_sale_container_deposit_inter_company/static/description/index.html
odoo/addons/purchase_sale_container_deposit_inter_company/tests/__init__.py
odoo/addons/purchase_sale_container_deposit_inter_company/tests/test_inter_company_purchase_sale_container_deposit.py
odoo_addon_purchase_sale_container_deposit_inter_company-16.0.1.0.2.2.dist-info/METADATA
odoo_addon_purchase_sale_container_deposit_inter_company-16.0.1.0.2.2.dist-info/WHEEL
odoo_addon_purchase_sale_container_deposit_inter_company-16.0.1.0.2.2.dist-info/top_level.txt
odoo_addon_purchase_sale_container_deposit_inter_company-16.0.1.0.2.2.dist-info/RECORD
