Metadata-Version: 2.1
Name: odoo-addon-purchase_sale_container_deposit_inter_company
Version: 16.0.1.0.2.2
Summary: Add compatibility between OCA product_packaging_container_deposit and purchase_sale_inter_company
Home-page: https://github.com/OCA/multi-company
Author: Camptocamp, Odoo Community Association (OCA)
Author-email: support@odoo-community.org
License: AGPL-3
Classifier: Programming Language :: Python
Classifier: Framework :: Odoo
Classifier: Framework :: Odoo :: 16.0
Classifier: License :: OSI Approved :: GNU Affero General Public License v3
Requires-Python: >=3.10
Requires-Dist: odoo-addon-purchase-product-packaging-container-deposit<16.1dev,>=16.0dev
Requires-Dist: odoo-addon-purchase-sale-inter-company<16.1dev,>=16.0dev
Requires-Dist: odoo-addon-sale-product-packaging-container-deposit<16.1dev,>=16.0dev
Requires-Dist: odoo<16.1dev,>=16.0a
